headers_workaround
