Metadata-Version: 1.1
Name: headers-workaround
Version: 0.12
Summary: Add this to setup_requires, and use it to fetch headers.
Home-page: http://github.com/syllog1sm/headers_workaround
Author: Matthew Honnibal
Author-email: honnibal@gmail.com
License: UNKNOWN
Platform: UNKNOWN
Classifier: Environment :: Console
Classifier: Operating System :: OS Independent
Classifier: Intended Audience :: Science/Research
Classifier: Programming Language :: Cython
Classifier: Topic :: Scientific/Engineering
